ronet/__init__.py
ronet/activations.py
ronet/layers.py
ronet/loss.py
ronet/model.py
ronet/optimizers.py
ronet/regularization.py
ronet-0.1.3.dist-info/licenses/LICENSE
ronet-0.1.3.dist-info/METADATA
ronet-0.1.3.dist-info/WHEEL
ronet-0.1.3.dist-info/top_level.txt
ronet-0.1.3.dist-info/RECORD
