Metadata-Version: 2.4
Name: ronet
Version: 0.1.3
Summary: A deep learning framework built on NumPy
Home-page: https://github.com/rohit-2304/ronet
Author: Rohit Gatne
Author-email: rohitgatne23@gmail.com
Classifier: Programming Language :: Python :: 3
Classifier: License :: OSI Approved :: MIT License
Classifier: Operating System :: OS Independent
Requires-Python: >=3.6
License-File: LICENSE
Requires-Dist: numpy
Requires-Dist: pandas
Dynamic: author
Dynamic: author-email
Dynamic: classifier
Dynamic: description
Dynamic: description-content-type
Dynamic: home-page
Dynamic: license-file
Dynamic: requires-dist
Dynamic: requires-python
Dynamic: summary
